MANIFEST.in
setup.py
docs/HISTORY.txt
docs/INSTALL.txt
docs/LICENSE.GPL
docs/LICENSE.txt
niteoweb/__init__.py
niteoweb.loginas.egg-info/PKG-INFO
niteoweb.loginas.egg-info/SOURCES.txt
niteoweb.loginas.egg-info/dependency_links.txt
niteoweb.loginas.egg-info/entry_points.txt
niteoweb.loginas.egg-info/namespace_packages.txt
niteoweb.loginas.egg-info/not-zip-safe
niteoweb.loginas.egg-info/requires.txt
niteoweb.loginas.egg-info/top_level.txt
niteoweb/loginas/README.txt
niteoweb/loginas/__init__.py
niteoweb/loginas/configure.zcml
niteoweb/loginas/browser/__init__.py
niteoweb/loginas/browser/configure.zcml
niteoweb/loginas/browser/login_as.pt
niteoweb/loginas/browser/login_as.py
niteoweb/loginas/locales/niteoweb.loginas.pot
niteoweb/loginas/locales/rebuild_i18n.sh
niteoweb/loginas/locales/es/LC_MESSAGES/niteoweb.loginas.po