Metadata-Version: 1.0
Name: niteoweb.loginas
Version: 0.2
Summary: Allow administrator to login as another user (useful for debugging).
Home-page: http://www.niteoweb.com/
Author: Niteoweb d.o.o.
Author-email: info@niteoweb.com
License: GNU GPL
Keywords: zope,plone
Platform: UNKNOWN
Classifier: Framework :: Plone
Classifier: Framework :: Zope2
Classifier: Framework :: Zope3
Classifier: Programming Language :: Python
Classifier: Topic :: Software Development :: Libraries :: Python Modules
